{"stats":{"minecraft:dropped":{"tutorial:tungsten_ore":1},"minecraft:custom":{"minecraft:jump":9,"minecraft:time_since_rest":1008,"minecraft:leave_game":1,"minecraft:play_time":1008,"minecraft:time_since_death":1008,"minecraft:walk_one_cm":3458,"minecraft:total_world_time":1030,"minecraft:drop":1},"minecraft:mined":{"tutorial:tungsten_ore":5},"minecraft:used":{"minecraft:stone_pickaxe":1,"minecraft:netherite_pickaxe":3,"minecraft:diamond_pickaxe":1},"minecraft:picked_up":{"tutorial:tungsten_ore":1}},"DataVersion":2724}